gamewire/__init__.py
gamewire/client.py
gamewire-1.0.0.dist-info/LICENSE
gamewire-1.0.0.dist-info/METADATA
gamewire-1.0.0.dist-info/WHEEL
gamewire-1.0.0.dist-info/top_level.txt
gamewire-1.0.0.dist-info/RECORD
