Metadata-Version: 2.1
Name: gamewire
Version: 1.0.0
Summary: A Python SDK for the Gamewire API
Home-page: https://github.com/yourusername/gamewire
Author: Gamewire
Author-email: support@gamewire.gg
Classifier: Development Status :: 3 - Alpha
Classifier: Intended Audience :: Developers
Classifier: License :: OSI Approved :: MIT License
Classifier: Operating System :: OS Independent
Classifier: Programming Language :: Python :: 3
Classifier: Programming Language :: Python :: 3.6
Classifier: Programming Language :: Python :: 3.7
Classifier: Programming Language :: Python :: 3.8
Classifier: Programming Language :: Python :: 3.9
Requires-Python: >=3.6
License-File: LICENSE
Requires-Dist: requests >=2.25.1
